<?xml version="1.0" encoding="UTF-8"?>
<con:soapui-project id="5f45e63e-4888-4c8c-8fab-24e42948d9b7" activeEnvironment="Default" name="Users API" resourceRoot="" soapui-version="5.7.2" abortOnError="false" runType="SEQUENTIAL" xmlns:con="http://eviware.com/soapui/config"><con:settings/><con:interface xsi:type="con:RestService" id="d0e68033-772d-48da-8f14-0082a72af0a4" wadlVersion="http://wadl.dev.java.net/2009/02" name="http://localhost:3000" type="rest" xmlns:xsi="http://www.w3.org/2001/XMLSchema-instance"><con:settings/><con:definitionCache/><con:endpoints><con:endpoint>http://localhost:3000</con:endpoint></con:endpoints><con:resource name="login" path="" id="cc49024d-4b5f-462e-98f4-1bafe29a2f77"><con:settings/><con:parameters/><con:method name="Method 1" id="fdfeef5f-375b-4f20-8ac2-89f33c7cc062" method="POST"><con:settings/><con:parameters/><con:representation type="FAULT"><con:mediaType>text/html; charset=utf-8</con:mediaType><con:status>404</con:status><con:params/><con:element>html</con:element></con:representation><con:representation type="REQUEST"><con:mediaType>application/json</con:mediaType><con:params/></con:representation><con:representation type="RESPONSE"><con:mediaType>text/html; charset=utf-8</con:mediaType><con:status>200</con:status><con:params/><con:element>html</con:element></con:representation><con:request name="login" id="bd8ef2fc-25ff-48a0-ba32-55dda11fb72d" mediaType="application/json" postQueryString="false"><con:settings><con:setting id="com.eviware.soapui.impl.wsdl.WsdlRequest@request-headers">&lt;xml-fragment/></con:setting></con:settings><con:endpoint>http://localhost:3000/api/login</con:endpoint><con:request>{
  "userName": "brox0rz",
  "password": "123"
}
</con:request><con:originalUri>http://localhost/api/login</con:originalUri><con:credentials><con:authType>No Authorization</con:authType></con:credentials><con:jmsConfig JMSDeliveryMode="PERSISTENT"/><con:jmsPropertyConfig/><con:parameters/></con:request></con:method></con:resource></con:interface><con:properties/><con:wssContainer/><con:oAuth2ProfileContainer/><con:oAuth1ProfileContainer/><con:sensitiveInformation/></con:soapui-project>